Metadata-Version: 1.0
Name: calculator-test-one
Version: 0.0.1
Summary: calculator 
Home-page: UNKNOWN
Author: Jihenbouguerra
Author-email: UNKNOWN
License: MIT
Platform: UNKNOWN
